finalsa/http/__init__.py
finalsa/http/_shared.py
finalsa/http/async_client/__init__.py
finalsa/http/async_client/base.py
finalsa/http/sync_client/__init__.py
finalsa/http/sync_client/base.py
finalsa_common_http_client-0.0.8.dist-info/METADATA
finalsa_common_http_client-0.0.8.dist-info/WHEEL
finalsa_common_http_client-0.0.8.dist-info/licenses/LICENSE.md
finalsa_common_http_client-0.0.8.dist-info/RECORD
