Metadata-Version: 2.4
Name: finalsa-common-http-client
Version: 0.0.8
Summary: HTTP client library for common data types used in business applications
Project-URL: Homepage, https://github.com/finalsa/finalsa-http-client
Project-URL: Documentation, https://github.com/finalsa/finalsa-http-client#readme
Project-URL: Repository, https://github.com/finalsa/finalsa-http-client.git
Project-URL: Issues, https://github.com/finalsa/finalsa-http-client/issues
Project-URL: Changelog, https://github.com/finalsa/finalsa-http-client/blob/main/CHANGELOG.md
Author-email: Luis Jimenez <luis@finalsa.com>
License: MIT License
License-File: LICENSE.md
Keywords: client,finalsa,http
Classifier: Development Status :: 4 - Beta
Classifier: Intended Audience :: Developers
Classifier: License :: OSI Approved :: MIT License
Classifier: Operating System :: OS Independent
Classifier: Programming Language :: Python :: 3
Classifier: Programming Language :: Python :: 3.10
Classifier: Programming Language :: Python :: 3.11
Classifier: Programming Language :: Python :: 3.12
Classifier: Programming Language :: Python :: 3.13
Classifier: Topic :: Software Development :: Internationalization
Classifier: Topic :: Software Development :: Libraries :: Python Modules
Classifier: Topic :: Software Development :: Localization
Classifier: Typing :: Typed
Requires-Python: >=3.10
Requires-Dist: aiohttp>=3.10.5
Requires-Dist: fastapi>=0.116.1
Requires-Dist: finalsa-common-models>=2.0.4
Requires-Dist: finalsa-traceability>=1.0.1
Requires-Dist: requests>=2.32.4
